remotejwt_auth/__init__.py
remotejwt_auth/authentication.py
remotejwt_auth/backends.py
remotejwt_auth/exceptions.py
remotejwt_auth/models.py
remotejwt_auth/py.typed
remotejwt_auth/serializers.py
remotejwt_auth/settings.py
remotejwt_auth/state.py
remotejwt_auth/tokens.py
remotejwt_auth/urls.py
remotejwt_auth/utils.py
remotejwt_auth/views.py
remotejwt_auth/token_blacklist/__init__.py
remotejwt_auth/token_blacklist/admin.py
remotejwt_auth/token_blacklist/apps.py
remotejwt_auth/token_blacklist/models.py
remotejwt_auth/token_blacklist/management/__init__.py
remotejwt_auth/token_blacklist/management/commands/__init__.py
remotejwt_auth/token_blacklist/management/commands/flushexpiredtokens.py
remotejwt_auth/token_blacklist/migrations/0001_initial.py
remotejwt_auth/token_blacklist/migrations/0002_outstandingtoken_jti_hex.py
remotejwt_auth/token_blacklist/migrations/0003_auto_20171017_2007.py
remotejwt_auth/token_blacklist/migrations/0004_auto_20171017_2013.py
remotejwt_auth/token_blacklist/migrations/0005_remove_outstandingtoken_jti.py
remotejwt_auth/token_blacklist/migrations/0006_auto_20171017_2113.py
remotejwt_auth/token_blacklist/migrations/0007_auto_20171017_2214.py
remotejwt_auth/token_blacklist/migrations/0008_migrate_to_bigautofield.py
remotejwt_auth/token_blacklist/migrations/0010_fix_migrate_to_bigautofield.py
remotejwt_auth/token_blacklist/migrations/0011_linearizes_history.py
remotejwt_auth/token_blacklist/migrations/0012_alter_outstandingtoken_user.py
remotejwt_auth/token_blacklist/migrations/__init__.py
remotejwt_client/__init__.py
remotejwt_client/admin.py
remotejwt_client/apps.py
remotejwt_client/authentication.py
remotejwt_client/models.py
remotejwt_client/serializers.py
remotejwt_client/settings.py
remotejwt_client/tests.py
remotejwt_client/urls.py
remotejwt_client/utils.py
remotejwt_client/views.py
remotejwt_client/migrations/__init__.py
remotejwt_client/tmp/__init__.py
remotejwt_client/tmp/authentication.py
remotejwt_client/tmp/py.typed
drf_remotejwt-0.3.2.dist-info/LICENCE
drf_remotejwt-0.3.2.dist-info/METADATA
drf_remotejwt-0.3.2.dist-info/WHEEL
drf_remotejwt-0.3.2.dist-info/top_level.txt
drf_remotejwt-0.3.2.dist-info/RECORD
