Metadata-Version: 2.1
Name: drf-remotejwt
Version: 0.3.2
Summary: A client and server packages to authenticate against and create a remote Authentication Service that support JWTs, think microservice authentication backend.
Home-page: https://github.com/garrethcain/drf-remotejwt
Author: Garreth Cain
Author-email: garrethccain@gmail.com
License: MIT
Classifier: Environment :: Web Environment
Classifier: Framework :: Django
Classifier: Framework :: Django :: 3.2
Classifier: Intended Audience :: Developers
Classifier: License :: OSI Approved :: BSD License
Classifier: Operating System :: OS Independent
Classifier: Programming Language :: Python
Classifier: Programming Language :: Python :: 3
Classifier: Programming Language :: Python :: 3 :: Only
Classifier: Programming Language :: Python :: 3.6
Classifier: Programming Language :: Python :: 3.7
Classifier: Programming Language :: Python :: 3.8
Classifier: Programming Language :: Python :: 3.9
Classifier: Programming Language :: Python :: 3.10
Classifier: Programming Language :: Python :: 3.11
Classifier: Programming Language :: Python :: 3.12
Classifier: Topic :: Internet :: WWW/HTTP
Classifier: Topic :: Internet :: WWW/HTTP :: Dynamic Content
Requires-Python: >=3.6
License-File: LICENCE
Requires-Dist: Django >=3.2
Requires-Dist: djangorestframework >=3.12.4
Requires-Dist: requests >=2.24.0
